jeteloss/__init__.py
jeteloss/jeteloss.py
jeteloss/data/RAA_2760.txt
jeteloss/data/pp_200.txt
jeteloss/data/pp_2760.txt
jeteloss/data/pp_5020.txt
jeteloss-0.7.dist-info/METADATA
jeteloss-0.7.dist-info/RECORD
jeteloss-0.7.dist-info/WHEEL
jeteloss-0.7.dist-info/top_level.txt
