Metadata-Version: 2.1
Name: jeteloss
Version: 0.7
Summary: Data-driven extraction of jet energy loss distributions in heavy-ion collisions
Home-page: https://github.com/lgpang/jeteloss
Author: Long-Gang Pang, Ya-Yun He and Xin-Nian Wang
Author-email: lgpang@qq.com, heyayun@gmail.com, xnwang@lbl.gov
License: MIT
Keywords: Bayesian,MCMC,Jet energy loss extractor,RAA
Platform: UNKNOWN
Classifier: Programming Language :: Python :: 3
Classifier: License :: OSI Approved :: MIT License
Classifier: Operating System :: OS Independent
Requires-Dist: numpy (>=1.14)
Requires-Dist: h5py (>=2.8.0)
Requires-Dist: scipy (>=1.1.0)
Requires-Dist: matplotlib (>=2.2.0)
Requires-Dist: pandas (>=0.23.3)
Requires-Dist: seaborn (>=0.7.1)
Requires-Dist: pymc (>=2.3.6)
